discogspy/__init__.py
discogspy/_nbdev.py
discogspy/core/__init__.py
discogspy/core/constants.py
discogspy/core/database_rq.py
discogspy/core/discogs_user.py
discogspy/core/rq_collection.py
discogspy/core/rq_database.py
discogspy/core/rq_inventory_export.py
discogspy/core/rq_inventory_upload.py
discogspy/core/rq_marketplace.py
discogspy/core/rq_userlists.py
discogspy/core/rq_wantlist.py
discogspy-0.6.0.dist-info/LICENSE
discogspy-0.6.0.dist-info/METADATA
discogspy-0.6.0.dist-info/WHEEL
discogspy-0.6.0.dist-info/entry_points.txt
discogspy-0.6.0.dist-info/top_level.txt
discogspy-0.6.0.dist-info/RECORD
