Metadata-Version: 2.1
Name: discogspy
Version: 0.6.0
Summary: A set of wrapper and tools to make use of the discogs api
Home-page: https://github.com/cpow-89/discogspy
Author: cpow-89
Author-email: christoph_powazny@gmx.de
License: Apache Software License 2.0
Keywords: python discogs requests api
Platform: UNKNOWN
Classifier: Development Status :: 3 - Alpha
Classifier: Intended Audience :: Developers
Classifier: License :: OSI Approved :: Apache Software License
Classifier: Natural Language :: English
Classifier: Programming Language :: Python :: 3.6
Classifier: Programming Language :: Python :: 3.7
Classifier: Programming Language :: Python :: 3.8
Requires-Python: >=3.6
Requires-Dist: jupyter
Requires-Dist: requests
Requires-Dist: responses
Requires-Dist: pandas
